kubesealer/cli.py
kubesealer/cluster.py
kubesealer/host.py
kubesealer/kubeseal.py
kubesealer-1.0.0.dist-info/LICENSE
kubesealer-1.0.0.dist-info/METADATA
kubesealer-1.0.0.dist-info/WHEEL
kubesealer-1.0.0.dist-info/entry_points.txt
kubesealer-1.0.0.dist-info/RECORD
